duckreporter/__init__.py
duckreporter/emitter.py
duckreporter/trace.py
duckreporter/worker.py
duckreporter-0.0.2.dist-info/METADATA
duckreporter-0.0.2.dist-info/WHEEL
duckreporter-0.0.2.dist-info/licenses/LICENSE
duckreporter-0.0.2.dist-info/RECORD
